{"cameraMode":{"drawMode":0,"name":"Shaded","section":"Shading Mode"},"sceneLighting":true,"audioPlay":false,"sceneViewState":{"m_AlwaysRefresh":false,"showFog":true,"showSkybox":true,"showFlares":true,"showImageEffects":true,"showParticleSystems":true,"showVisualEffectGraphs":true,"m_FxEnabled":true},"in2DMode":false,"pivot":{"x":41.25949478149414,"y":17.56110191345215,"z":-13.603157043457032},"rotation":{"x":-0.10299895703792572,"y":0.8577564358711243,"z":-0.1916685700416565,"w":-0.4660504162311554},"size":6.739231109619141,"orthographic":false}